gcg/__init__.py
gcg/entrypoint.py
gcg/errors.py
gcg/jinja_filters.py
gcg/tag_filter.py
gcg/templates/deb
gcg/templates/rpm
gcg-0.2.0.dist-info/LICENSE
gcg-0.2.0.dist-info/METADATA
gcg-0.2.0.dist-info/WHEEL
gcg-0.2.0.dist-info/entry_points.txt
gcg-0.2.0.dist-info/top_level.txt
gcg-0.2.0.dist-info/RECORD
