Metadata-Version: 2.1
Name: gcg
Version: 0.2.0
Summary: Git Changelog Generator
Home-page: https://github.com/nokia/git-changelog-generator
Author: Waldek Maleska
Author-email: waldek.maleska@nokia.com
License: BSD-3-Clause
Platform: UNKNOWN
Classifier: Development Status :: 3 - Alpha
Classifier: Environment :: Console
Classifier: Programming Language :: Python
Classifier: Programming Language :: Python :: 2
Classifier: Topic :: Software Development :: Bug Tracking
Classifier: Topic :: Software Development :: Build Tools
Classifier: Topic :: Software Development :: Version Control :: Git
Classifier: Topic :: System :: Software Distribution
Classifier: Topic :: Utilities
Classifier: License :: OSI Approved :: BSD License
Requires-Dist: jinja2 (>=2.10)
Requires-Dist: semver (>=2.0.1)
Requires-Dist: GitPython (>=1.0.1)
